{
  "${ModID}:OttosDeck": {
    "NAME": "Доска Отто",
    "FLAVOR": "Доска Отто сделана в стиле шахмат. Хмям.",
    "DESCRIPTIONS": [
      "При получении заменяет все #yУдары и #yОбороны в колоде на #yПомощь #yпешек. Добавляет в колоду случ. #bНеобычную и случ. #yРедкую #pкарту #pшахмат."
    ]
  },
  "${ModID}:CardboardHeart": {
    "NAME": "Сердце из картона",
    "FLAVOR": "Колоды убитых приключенцев образовали этот волокнистый кусок.",
    "DESCRIPTIONS": [
      "В начале боя выберите между ",
      ", ",
      " и ",
      ". Добавляет выбранную карту в руку с #y«Оставляется».",
      "Выберите карту, которую хотите добавить в руку.",
      "При получении выбирает #b3 случ. карты. Выберите и добавьте в руку #b1 из #b3 этих карт с #y«Оставляется» в начале боя."
    ]
  },
  "${ModID}:BucketOfSlime": {
    "NAME": "Ведро слизи",
    "FLAVOR": "Ведро слизи! Полезное и универсальное! А? Где применимо? Я просто торговец, придумайте сами.",
    "DESCRIPTIONS": [
      "Даëт #b%d #yЗащиты при первом разыгрывании каждой карты в бою."
    ]
  },
  "${ModID}:WarBannerCultist": {
    "NAME": "Боевое знамя культиста",
    "FLAVOR": "Кар? Кар Кар! Кар.  кар.",
    "DESCRIPTIONS": [
      "Даёт #b1 #yРитуала и отнимает #b2 #yСилы в начале боя.",
      "#gПолучить #gБоевое #gзнамя #gкультиста."
    ]
  },
  "${ModID}:WarBannerLouse": {
    "NAME": "Боевое знамя воши",
    "FLAVOR": "Думай как жук. Стань жуком.",
    "DESCRIPTIONS": [
      "Даёт #b10 #yСвернуться в начале боя. #yЗащита не исчезнет на один ход, после срабатывания #yСвернуться.",
      "#gПолучить #gБоевое #gзнамя #gвоши."
    ]
  },
  "${ModID}:WarBannerNob": {
    "NAME": "Боевое знамя верзилы",
    "FLAVOR": "РРаааАрГГх!!",
    "DESCRIPTIONS": [
      "Даёт #b1 #yСилы, первые #b%d намерения врага, которые не являются атаками. Даёт #b%d #yСлабости в начале боя.",
      "#gПолучить #gБоевое #gзнамя #gверзилы."
    ]
  },
  "${ModID}:WarBannerSnecko": {
    "NAME": "Боевое знамя змекко",
    "FLAVOR": "Этот узор. Он так... завораживает.",
    "DESCRIPTIONS": [
      "Накладывает на вас #yЗамешательство в начале боя. Вы берёте на #b3 карты больше в начале боя.",
      "#gПолучить #gБоевое #gзнамя #gзмекко."
    ]
  },
  "${ModID}:Torch": {
    "NAME": "Факел",
    "FLAVOR": "Простой факел, который светится изумрудным пламенем. Похоже, он становится слабее со временем.",
    "DESCRIPTIONS": [
      "В начале боя добавляет #b2 копии ",
      " в стопку добора, пока вы находитесь в #yбашне.",
      "В начале боя добавляет #b2 копии выбранной карты в стопку добора, пока вы находитесь в #yбашне.",
      "Просто палка."
    ]
  },
  "${ModID}:Lucky": {
    "NAME": "Везение",
    "FLAVOR": "Те, кто отдаёт что-нибудь менее везучим, всегда оказываются вознаграждены.",
    "DESCRIPTIONS": [
      "Даёт #b1 #yСилы и #b1 #yЛовкости в начале битвы с боссом башни."
    ]
  },
  "${ModID}:IronPotHelmet": {
    "NAME": "Шлем железного горшка",
    "FLAVOR": "Когда-то он был особенным и зачарованным. Теперь это лишь большой кусок металла.",
    "DESCRIPTIONS": [
      "Даёт #b3 #yЗащиты, когда вы разыгрываете #yОборону."
    ]
  },
  "${ModID}:DijinnLamp": {
    "NAME": "Лампа Джина",
    "FLAVOR": "Потерев, можно почувствовать слабые отголоски безграничной силы",
    "DESCRIPTIONS": [
      "Добавляет в стопку добора #yПолученное #yжелание в начале боя."
    ]
  },
  "${ModID}:CursedDoll": {
    "NAME": "Проклятая кукла",
    "FLAVOR": "Проколота множеством иголок и булавок... и выглядит на удивление схоже с вами.",
    "DESCRIPTIONS": [
      "Отнимает ОЗ у ВСЕХ врагов, равные удвоенному получаемому урону по ОЗ."
    ]
  },
  "${ModID}:GreedBlight": {
    "NAME": "Проклятие жадности",
    "FLAVOR": "Богатство притягивает жадность.",
    "DESCRIPTIONS": [
      "Увеличивает стоимость реликвий в магазине в #b%dx."
    ]
  },
  "${ModID}:VoidBlight": {
    "NAME": "Пустая душа",
    "FLAVOR": "Ты не ценишь того что имеешь пока не потеряешь.",
    "DESCRIPTIONS": [
      "Добавляет в стопку добора #yБездну в начале боя."
    ]
  },
  "${ModID}:PromiseOfGold": {
    "NAME": "Обещание золота",
    "FLAVOR": "Это будет того стоить.",
    "DESCRIPTIONS": [
      "Даёт #b{0} #yзолота после победы над боссом #yбашни."
    ]
  },
  "${ModID}:ClericsBlessing": {
    "NAME": "Благословение клирика",
    "FLAVOR": "Оно определённо дружелюбно.",
    "DESCRIPTIONS": [
      "Даёт #b{0} #yЛовкости в начале боя, пока вы в башне.."
    ]
  },
  "${ModID}:ArmorersMask": {
    "NAME": "Шлем оружейника",
    "FLAVOR": "Часть стаи!",
    "DESCRIPTIONS": [
      "Вы стали на редкость болтливы и начинаете бой с #b1 #yЛовкости.",
      "@КАР!@ NL @КАААР@"
    ]
  },
  "${ModID}:AlphabetSoup": {
    "NAME": "Буквенный суп",
    "FLAVOR": "Обуквеительнеше.",
    "DESCRIPTIONS": [
      "Выберите и добавьте в руку #b1 из #b3 карт начинающихся с определённой буквы в начале боя. Вы получаете #b2 #yЗащиты и [E] , когда разыгрываете карту начинающуюся с этой буквы.",
      "Выберите и добавьте в руку #b1 из #b3 карт начинающихся с буквы #p«",
      "». Вы получаете #b4 #yЗащиты и [E] , когда разыгрываете карту начинающуюся с буквы #p«",
      "».",
      "Выберите карту, которую хотите добавить в руку."
    ]
  },
  "${ModID}:GorgonHead": {
    "NAME": "Голова горгоны",
    "FLAVOR": "На неё всё ещё опасно смотреть.",
    "DESCRIPTIONS": [
      "Отнимает #b1 временной #yСилы у врага, который впервые за бой намеревается атаковать несколько раз."
    ]
  },
  "${ModID}:SlimeFilledFlask": {
    "NAME": "Фляга слизи",
    "FLAVOR": "Это вообще можно пить?",
    "DESCRIPTIONS": [
      "Добавляет в руку #yСлизнексир в начале боя."
    ]
  },
  "${ModID}:SentryOrb": {
    "NAME": "Ядро часового",
    "FLAVOR": "Зловещая энергия всё ещё пульсирует внутри после извлечения.",
    "DESCRIPTIONS": [
      "Наносит #b"," урона случ. врагу в начале каждого #bнечётного хода.",
      "Урона нанесла: "," NL За бой: "," NL За ход: "
    ]
  },
  "${ModID}:SweatyArmband": {
    "NAME": "Мокрая повязка",
    "FLAVOR": "Нет страданий. Нет плюшек.",
    "DESCRIPTIONS": [
      "Даёт #b1 #yСилы, когда вы получаете урон по ОЗ."
    ]
  },
    "${ModID}:JadeIdol": {
    "NAME": "Нефритовый идол",
    "FLAVOR": "Безупречно вырезан и отрицает физику, всего один из них со временем становится очень сильным.",
    "DESCRIPTIONS": [
      "Добавляет в руку #yВоздушный #yудар в начале боя.",
      "Предпросмотр"
    ]
  },
  "${ModID}:RubyFragment": {
    "NAME": "Кусочек рубина",
    "FLAVOR": "Всего лишь осколок силы Судьи, видимо перступление было вознаграждено его божественностью.",
    "DESCRIPTIONS": [
      "Вы получаете [E] и берёте #b2 карты при нанесении #b15 урона по ОЗ. Один раз за бой."
    ]
  },
  "${ModID}:ScaryNail": {
    "NAME": "Ужасающий гвоздь",
    "FLAVOR": "Вытащен из тотема, он будет хорошо смотреться в бейсбольной бите.",
    "DESCRIPTIONS": [
      "Даёт #b%d #yСилы за каждого врага в начале боя."
    ]
  },
  "${ModID}:QueensPawn": {
    "NAME": "Пешка ферзя",
    "FLAVOR": "Из всех фигур самая важная и преданная.",
    "DESCRIPTIONS": [
      "Наносит #b5 урона случайному врагу, если первая и последняя разыгранная карта это #yАтака. NL Даёт #b5 #yЗащиты, если первая и последняя разыгранная карта это #yНавык."
    ]
  },
  "${ModID}:SteelboundCodex": {
    "NAME": "Кодекс стали",
    "FLAVOR": "Окей, Intellij, почему ты хочешь исправить «Steelbound» на «Spellbound»?!?",
    "DESCRIPTIONS": [
      "Потратив [E] [E] [E] на #yАтаки, вы снижаете стоимость след. #yАтаки до #b0."
    ]
  }
}


